bsql/__init__.py
bsql/backends.py
bsql/database.py
bsql/enums.py
bsql/misc.py
bsql/py.typed
bsql/statement.py
bsql/table.py
barkshark_sql-0.2.1.dist-info/LICENSE
barkshark_sql-0.2.1.dist-info/METADATA
barkshark_sql-0.2.1.dist-info/WHEEL
barkshark_sql-0.2.1.dist-info/top_level.txt
barkshark_sql-0.2.1.dist-info/RECORD
