Metadata-Version: 2.2
Name: barkshark-sql
Version: 0.2.1
Summary: Connection pool and query builder for dbapi 2.0 database drivers
Author-email: Zoey Mae <admin@barkshark.xyz>
License:                     GNU GENERAL PUBLIC LICENSE
Project-URL: Documentation, https://docs.barkshark.xyz/barkshark-sql
Project-URL: Source, https://codeberg.org/barkshark/bsql
Keywords: sql,database,sqlite,postgresql
Platform: any
Classifier: Development Status :: 4 - Beta
Classifier: Intended Audience :: Developers
Classifier: License :: OSI Approved :: GNU General Public License v3 or later (GPLv3+)
Classifier: Operating System :: OS Independent
Classifier: Programming Language :: Python
Classifier: Programming Language :: Python :: 3.10
Classifier: Programming Language :: Python :: 3.11
Classifier: Programming Language :: Python :: 3.12
Classifier: Programming Language :: Python :: 3.13
Classifier: Programming Language :: Python :: Implementation :: CPython
Classifier: Programming Language :: Python :: Implementation :: PyPy
Classifier: Topic :: Database
Classifier: Typing :: Typed
Requires-Python: >=3.10
License-File: LICENSE
Requires-Dist: pg8000
Provides-Extra: docs
Requires-Dist: furo==2024.1.29; extra == "docs"
Requires-Dist: sphinx==7.2.6; extra == "docs"
Requires-Dist: sphinx-external-toc==1.0.1; extra == "docs"
Provides-Extra: dev
Requires-Dist: mypy==1.10.1; extra == "dev"
Requires-Dist: flake8==7.1.0; extra == "dev"
Requires-Dist: typing_extensions>=4.10.0; python_version < "3.11.0" and extra == "dev"
